mstool/__init__.py
mstool/authors.py
mstool/version.py
mstool/FF/amber14/DNA.OL15.xml
mstool/FF/amber14/DNA.bsc1.xml
mstool/FF/amber14/RNA.OL3.xml
mstool/FF/amber14/amber14-all.xml
mstool/FF/amber14/lipid17.xml
mstool/FF/amber14/protein.ff14SB.xml
mstool/FF/amber14/protein.ff15ipq.xml
mstool/FF/amber14/spce.xml
mstool/FF/amber14/tip3p.xml
mstool/FF/amber14/tip3pfb.xml
mstool/FF/amber14/tip4pew.xml
mstool/FF/amber14/tip4pfb.xml
mstool/FF/amber99/amber99sbildn.xml
mstool/FF/amber99/tip3p.xml
mstool/FF/charmm36/charmm36.xml
mstool/FF/charmm36/chyo.xml
mstool/FF/charmm36/clol.xml
mstool/FF/charmm36/pip.xml
mstool/FF/charmm36/triv.xml
mstool/FF/charmm36/water.xml
mstool/FF/martini2.2/martini_lipids_add.itp
mstool/FF/martini2.2/martini_v2.0_ions.itp
mstool/FF/martini2.2/martini_v2.0_lipids_all_201506.itp
mstool/FF/martini2.2/martini_v2.2.itp
mstool/FF/martini2.2/martini_v2.2.modified.LJ.itp
mstool/FF/martini2.2/martini_v2.2.modified.itp
mstool/FF/martini2.2/ti.itp
mstool/FF/martini2.2/toy.itp
mstool/FF/martini2.2/tp.itp
mstool/FF/martini2.2/structures/CHL1.pdb
mstool/FF/martini2.2/structures/CHOL.pdb
mstool/FF/martini2.2/structures/P005.pdb
mstool/FF/martini2.2/structures/P006.pdb
mstool/FF/martini2.2/structures/P007.pdb
mstool/FF/martini2.2/structures/P008.pdb
mstool/FF/martini2.2/structures/P010.pdb
mstool/FF/martini3.0.0/lipids.itp
mstool/FF/martini3.0.0/martini.itp
mstool/FF/martini3.0.0/phospholipids.itp
mstool/FF/martini3.0.0/protein.itp
mstool/backup/amberselection_20240510.py
mstool/backup/backmap.py
mstool/backup/bilayer_240429.py
mstool/backup/bilayerbuilder_240429.py
mstool/backup/fill.bck.py
mstool/backup/fill_loops.py
mstool/backup/fill_side.py
mstool/backup/gmx2dms2.py
mstool/backup/loopmodeler_230719.py
mstool/backup/martinizedms.231213.py
mstool/backup/martinizedms.240309.py
mstool/backup/openmmutils_230719.py
mstool/backup/orient_240621.py
mstool/backup/pandas2dict.py
mstool/backup/rem.bck.py
mstool/backup/rem_230719.py
mstool/backup/rem_230801.py
mstool-0.3.9.dist-info/LICENSE
mstool-0.3.9.dist-info/METADATA
mstool-0.3.9.dist-info/WHEEL
mstool-0.3.9.dist-info/top_level.txt
mstool-0.3.9.dist-info/RECORD
