Metadata-Version: 2.1
Name: mstool
Version: 0.3.9
Summary: Multiscale Simulation Tool for Backmapping
Author-email: Siyoung Kim <siyoung.k@icloud.com>
License: GNU GENERAL PUBLIC LICENSE
Project-URL: Repository, https://github.com/ksy141/mstool.git
Project-URL: documentation, https://mstool.readthedocs.io/en/latest/#
Requires-Python: >=3.7
License-File: LICENSE
Requires-Dist: pandas
Requires-Dist: matplotlib
Requires-Dist: scipy
